wgaio/__init__.py
wgaio-0.0.1.dist-info/LICENSE
wgaio-0.0.1.dist-info/WHEEL
wgaio-0.0.1.dist-info/METADATA
wgaio-0.0.1.dist-info/RECORD
