Metadata-Version: 2.1
Name: wgaio
Version: 0.0.1
Summary: Asynchronous Wargaming API client
Home-page: https://github.com/SergeyTsaplin/wgaio
License: MIT
Author: Sergey Tsaplin
Author-email: me@sergeytsaplin.com
Maintainer: Sergey Tsaplin
Maintainer-email: me@sergeytsaplin.com
Requires-Python: >=3.10,<4.0
Classifier: License :: OSI Approved :: MIT License
Classifier: Programming Language :: Python :: 3
Classifier: Programming Language :: Python :: 3.10
Project-URL: Repository, https://github.com/SergeyTsaplin/wgaio
